akinator/__init__.py
akinator/async_client.py
akinator/client.py
akinator/exceptions.py
akinator-2.0.1.dist-info/licenses/LICENSE
akinator-2.0.1.dist-info/METADATA
akinator-2.0.1.dist-info/WHEEL
akinator-2.0.1.dist-info/top_level.txt
akinator-2.0.1.dist-info/RECORD
