Metadata-Version: 2.4
Name: akinator
Version: 2.0.1
Summary: A basic API wrapper for Akinator.
Home-page: https://github.com/Ombucha/akinator.py
Author: Omkaar
Author-email: omkaar.nerurkar@gmail.com
License: MIT
Classifier: License :: OSI Approved :: MIT License
Classifier: Natural Language :: English
Classifier: Programming Language :: Python
Classifier: Programming Language :: Python :: 3
Requires-Python: >= 3.9.0
License-File: LICENSE
Requires-Dist: cloudscraper
Dynamic: author
Dynamic: author-email
Dynamic: classifier
Dynamic: description
Dynamic: description-content-type
Dynamic: home-page
Dynamic: license
Dynamic: license-file
Dynamic: requires-dist
Dynamic: requires-python
Dynamic: summary
